live_parking_norwich/__init__.py
live_parking_norwich/src/__init__.py
live_parking_norwich/src/config.py
live_parking_norwich/src/helpers.py
live_parking_norwich/src/live_parking_norwich.py
live_parking_norwich/src/structures.py
live_parking_norwich/test/__init__.py
live_parking_norwich/test/test_live_parking_norwich.py
live_parking_norwich-0.0.2.dist-info/LICENCE
live_parking_norwich-0.0.2.dist-info/METADATA
live_parking_norwich-0.0.2.dist-info/WHEEL
live_parking_norwich-0.0.2.dist-info/top_level.txt
live_parking_norwich-0.0.2.dist-info/RECORD
