Metadata-Version: 2.1
Name: live_parking_norwich
Version: 0.0.2
Summary: This package provides real-time information about available parking spaces in car parks and park & ride sites around Norwich.
Home-page: https://github.com/exactful/live-parking-norwich
Author: Daniel Cooper
License: UNKNOWN
Keywords: parking parking-spaces park-and-ride Norwich
Platform: UNKNOWN
Classifier: Development Status :: 4 - Beta
Classifier: Intended Audience :: Developers
License-File: LICENCE
